{
  "sn7.20:0.1": "Linked Discourses 7.20 ",
  "sn7.20:0.2": "2. Lay Followers ",
  "sn7.20:0.3": "An Almsman ",
  "sn7.20:1.1": "1\nAt Sāvatthī. Then a mendicant brahmin approached the Blessed One … and said to him: \"Master Gotama, I am a mendicant and you are a mendicant. What is the difference between us in this respect?\"",
  "sn7.20:2.1": "",
  "sn7.20:2.2": "2\n\"It is not thus that one becomes a mendicant,\nJust because one begs others for alms.\nIf one has taken up a domestic practice,\nOne still has not become a bhikkhu.\n3\n\"But one here who leads the holy life,\nHaving expelled merit and evil,\nWho fares in the world with comprehension:\nHe is truly called a bhikkhu.\"",
  "sn7.20:2.3": "4\nWhen this was said, the mendicant brahmin said to the Blessed One: \"Magnificent, Master Gotama! Magnificent, Master Gotama! … Let Master Gotama remember me as a lay follower who from today has gone for refuge for life.\""
}