{
  "sn23.19:0.1": "Linked Discourses 23.19 ",
  "sn23.19:0.2": "2. About Māra (2nd) ",
  "sn23.19:0.3": "Liable To End ",
  "sn23.19:1.1": "At Sāvatthī. Sitting to one side, the Venerable Radha said to the Blessed One: \"Venerable sir, it is said, ‘subject to destruction, subject to destruction.’ What now, venerable sir, is subject to destruction?\"",
  "sn23.19:1.2": "\"Form, Radha, is subject to destruction. Feeling … Perception … Volitional formations … Consciousness is subject to destruction. Seeing thus … He understands: ’ … there is no more for this state of being.’\""
}