{
  "it:61.1": "61 – Eyes",
  "it:61.2": "This was said by the Blessed One, said by the Arahant, so I have heard:",
  "it:61.3": "\"There are these three eyes. Which three? The eye of flesh, the divine eye\n, and the eye of discernment. These are the three eyes.\"\nThe eye of flesh, the eye divine, the eye of discernment unsurpassed: these three eyes were taught by the Superlative Person.",
  "it:61.4": "The arising of the eye of flesh is the path to the eye divine. When knowledge arises, the eye of discernment unsurpassed: whoever gains this eye is — from all suffering — set free.",
  "it:61.5": "This, too, was the meaning of what was said by the Blessed One, so I have heard."
}