{
  "sn55.2:0.1": "Saṁyutta Nikāya 55.2 ",
  "sn55.2:0.2": "1. Veḷudvāravagga ",
  "sn55.2:0.3": "Brahmacariyogadhasutta ",
  "sn55.2:1.1": "\"Catūhi, bhikkhave, dhammehi samannāgato ariyasāvako sotāpanno hoti avinipātadhammo niyato sambodhiparāyaṇo.",
  "sn55.2:1.2": "Katamehi catūhi? Idha, bhikkhave, ariyasāvako buddhe aveccappasādena samannāgato hoti: ‘itipi so bhagavā arahaṁ sammāsambuddho vijjācaraṇasampanno sugato lokavidū anuttaro purisadammasārathi satthā devamanussānaṁ buddho bhagavā’ti. Dhamme … pe … saṅghe … pe … ariyakantehi sīlehi samannāgato hoti akhaṇḍehi … pe … samādhisaṁvattanikehi.",
  "sn55.2:1.3": "Imehi kho, bhikkhave, catūhi dhammehi samannāgato ariyasāvako sotāpanno hoti avinipātadhammo niyato sambodhiparāyaṇo\"ti.",
  "sn55.2:1.4": "Idamavoca bhagavā. Idaṁ vatvāna sugato athāparaṁ etadavoca satthā:",
  "sn55.2:1.5": "\"Yesaṁ saddhā ca sīlañca,\nPasādo dhammadassanaṁ;\nTe ve kālena paccenti,\nBrahmacariyogadhaṁ sukhan\"ti.\nDutiyaṁ."
}