{
  "sn3.1:0.1": "<article id='sn3.1'><header><ul><li class='division'>{}</li>",
  "sn3.1:0.2": "<li>{}</li></ul>",
  "sn3.1:0.3": "<h1 class='sutta-title'>{}</h1></header>",
  "sn3.1:1.1": "<p id=\"p1\"><span class=\"parno\">{}</span>{}</p>",
  "sn3.1:1.2": "<p>{}</p>",
  "sn3.1:1.3": "<p id=\"p2\"><span class=\"parno\">{}</span>{}</p>",
  "sn3.1:1.4": "<p id=\"p3\"><span class=\"parno\">{}</span>{}</p>",
  "sn3.1:1.5": "<p id=\"p4\"><span class=\"parno\">{}</span>{}</p>",
  "sn3.1:2.1": "<hr/>",
  "sn3.1:2.2": "<p class=\"verse\" id=\"p5\"><span class=\"parno\" id=\"v374\">{}</span>{}<br/>{}<br/>{}<br/>{}</p>",
  "sn3.1:2.3": "<p class=\"verse\" id=\"p6\"><span class=\"parno\" id=\"v375\">{}</span>{}<br/>{}<br/>{}<br/>{}<br/>{}<br/>{}</p>",
  "sn3.1:2.4": "<p class=\"verse\" id=\"p7\"><span class=\"parno\" id=\"v376\">{}</span>{}<br/>{}<br/>{}<br/>{}</p>",
  "sn3.1:2.5": "<p class=\"verse\" id=\"p8\"><span class=\"parno\" id=\"v377\">{}</span>{}<br/>{}\n<br/>{}<br/>{}<br/>{}<br/>{}</p>",
  "sn3.1:2.6": "<p class=\"verse\" id=\"p9\"><span class=\"parno\" id=\"v378\">{}</span>{}<br/>{}<br/>{}<br/>{}</p>",
  "sn3.1:2.7": "<p class=\"verse\" id=\"p10\"><span class=\"parno\" id=\"v379\">{}</span>{}<br/>{}<br/>{}<br/>{}<br/>{}<br/>{}</p>",
  "sn3.1:2.8": "<p class=\"verse\" id=\"p11\"><span class=\"parno\" id=\"v380\">{}</span>{}<br/>{}<br/>{}<br/>{}</p>",
  "sn3.1:2.9": "<p class=\"verse\" id=\"p12\"><span class=\"parno\" id=\"v381\">{}</span>{}<br/>{}<br/>{}<br/>{}<br/>{}<br/>{} </p>",
  "sn3.1:2.10": "<p class=\"verse\" id=\"p13\"><span class=\"parno\" id=\"v382\">{}</span>{}<br/>{}<br/>{}<br/>{}<br/>{}<br/>{}</p>",
  "sn3.1:2.11": "<p id=\"p14\"><span class=\"parno\">{}</span>{}</p>"
}