{
  "an10.155:0.1": "Numbered Discourses 10.155 ",
  "an10.155:0.2": "16. Persons ",
  "an10.155:0.3": "You Should Associate ",
  "an10.155:1.1": "1\n\"Bhikkhus, one should not associate with a person who possesses ten qualities. What ten?\nWrong view, wrong intention, wrong speech, wrong action, wrong livelihood, wrong effort, wrong mindfulness, wrong concentration, wrong knowledge, and wrong liberation. One should not associate with a person who possesses these ten qualities.",
  "an10.155:1.2": "2\n\"Bhikkhus, one should associate with a person who possesses ten qualities. What ten? Right view, right intention, right speech, right action, right livelihood, right effort, right mindfulness, right concentration, right knowledge, and right liberation. One should associate with a person who possesses these ten qualities.\""
}