{
  "mn142:0.1": "<article id='mn142'><header><ul><li class='division'>{}</li></ul>",
  "mn142:0.2": "<h1 class='sutta-title'>{}</h1></header>",
  "mn142:1.1": "<p id=\"p1\"><span class=\"parno\">{}</span>{}</p>",
  "mn142:1.2": "<p>{}{}</p>",
  "mn142:1.3": "<p>{}</p>",
  "mn142:2.1": "<hr/>",
  "mn142:2.2": "<p id=\"p2\"><span class=\"parno\">{}</span>{}</p>",
  "mn142:2.3": "<p id=\"p3\"><span class=\"parno\">{}</span>{}</p>",
  "mn142:3.1": "<hr/>",
  "mn142:3.2": "<p id=\"p4\"><span class=\"parno\">{}</span>{}{}</p>",
  "mn142:3.3": "<p id=\"p5\"><span class=\"parno\">{}</span>{}</p>",
  "mn142:3.4": "<p id=\"p6\"><span class=\"parno\">{}</span>{}</p>",
  "mn142:4.1": "<hr/>",
  "mn142:4.2": "<p id=\"p7\"><span class=\"parno\">{}</span>{}</p>",
  "mn142:4.3": "<p id=\"p8\"><span class=\"parno\">{}</span>{}</p>",
  "mn142:5.1": "<hr/>",
  "mn142:5.2": "<p id=\"p9\"><span class=\"parno\">{}</span>{}{}{}{}</p>",
  "mn142:5.3": "<p id=\"p10\"><span class=\"parno\">{}</span>{}{}{}</p><p>{}</p>",
  "mn142:5.4": "<p id=\"p11\"><span class=\"parno\">{}</span>{}{}{}{}</p>",
  "mn142:6.1": "<hr/>",
  "mn142:6.2": "<p id=\"12\"><span class=\"parno\">{}</span>{}{}{}</p>",
  "mn142:6.3": "<p id=\"p13\"><span class=\"parno\">{}</span>{}{}</p>",
  "mn142:6.4": "<p id=\"p14\"><span class=\"parno\">{}</span>{}</p>",
  "mn142:6.5": "<p id=\"p15\"><span class=\"parno\">{}</span>{}</p>",
  "mn142:6.6": "<p id=\"p16\"><span class=\"parno\">{}</span>{}</p>",
  "mn142:6.7": "<p id=\"p17\"><span class=\"parno\">{}</span>{}</p>",
  "mn142:7.1": "<hr/>",
  "mn142:7.2": "<p id=\"p18\"><span class=\"parno\">{}</span>{}</p>",
  "mn142:7.3": "<p class=\"verse\" id=\"p19\"><span class=\"parno\">{}</span>{}<br/>{}<br/>{}<br/>{}</p>",
  "mn142:7.4": "<p class=\"verse\" id=\"p20\"><span class=\"parno\">{}</span>{}<br/>{}<br/>{}<br/>{}</p>",
  "mn142:7.5": "<p class=\"verse\" id=\"p21\"><span class=\"parno\">{}</span>{}<br/>{}<br/>{}<br/>{}</p>",
  "mn142:7.6": "<p class=\"verse\" id=\"p22\"><span class=\"parno\">{}</span>{}<br/>{}<br/>{}<br/>{}</p>",
  "mn142:7.7": "<p class=\"verse\" id=\"p23\"><span class=\"parno\">{}</span>{}<br/>{}<br/>{}<br/>{}</p>",
  "mn142:8.1": "<hr/>"
}