{
  "mn152:0.1": "<article id='mn152'><header><ul><li class='division'>{}</li></ul>",
  "mn152:0.2": "<h1 class='sutta-title'>{}</h1></header>",
  "mn152:1.1": "<p id=\"p1\"><span class=\"parno\">{}</span>{}</p>",
  "mn152:1.2": "<p>{}</p><p>{}</p>",
  "mn152:2.1": "<hr/>",
  "mn152:2.2": "<p>{}</p>",
  "mn152:2.3": "<p>{}</p>",
  "mn152:2.4": "<p>{}</p>",
  "mn152:2.5": "<p>{}</p>",
  "mn152:2.6": "<p id=\"p2\"><span class=\"parno\">{}</span>{}</p>",
  "mn152:2.7": "<p>{}</p>",
  "mn152:3.1": "<hr/>",
  "mn152:3.2": "<p>{}</p>",
  "mn152:3.3": "<p>{}</p>",
  "mn152:4.1": "<hr/>",
  "mn152:4.2": "<p id=\"p3\"><span class=\"parno\">{}</span>{}{}{}</p>",
  "mn152:5.1": "<hr/>",
  "mn152:5.2": "<p id=\"p4\"><span class=\"parno\">{}</span>{}</p>",
  "mn152:5.3": "<p id=\"p5\"><span class=\"parno\">{}</span>{}</p>",
  "mn152:5.4": "<p id=\"p6\"><span class=\"parno\">{}</span>{}</p>",
  "mn152:5.5": "<p id=\"p7\"><span class=\"parno\">{}</span>{}</p>",
  "mn152:5.6": "<p id=\"p8\"><span class=\"parno\">{}</span>{}{}</p>",
  "mn152:5.7": "<p>{}</p>",
  "mn152:6.1": "<hr/>",
  "mn152:6.2": "<p id=\"p9\"><span class=\"parno\">{}</span>{}{}</p>",
  "mn152:7.1": "<hr/>",
  "mn152:7.2": "<p><span class=\"parno\">{}</span>{}{}{}{}</p>",
  "mn152:8.1": "<hr/>",
  "mn152:8.2": "<p id=\"p12\"><span class=\"parno\">{}</span>{}</p>",
  "mn152:8.3": "<p>{}</p>",
  "mn152:8.4": "<p id=\"p13\"><span class=\"parno\">{}</span>{}</p>",
  "mn152:9.1": "<hr/>"
}