{
  "mn97:1.1": "<p id=\"p1\"><span class=\"parno\">{}</span>{}</p>",
  "mn97:1.2": "<p>{}</p>",
  "mn97:2.1": "<p>{}</p>",
  "mn97:2.2": "<p>{}</p>",
  "mn97:2.3": "<p>{}</p>",
  "mn97:2.4": "<p>{}</p>",
  "mn97:2.5": "<p>{}</p>",
  "mn97:2.6": "<p>{}</p>",
  "mn97:2.7": "<p>{}</p>",
  "mn97:2.8": "<p>{}</p>",
  "mn97:3.1": "<p id=\"p2\"><span class=\"parno\">{}</span>{}</p>",
  "mn97:3.2": "<p>{}</p>",
  "mn97:3.3": "<p>{}</p>",
  "mn97:3.4": "<p>{}</p>",
  "mn97:3.5": "<p>{}</p>",
  "mn97:3.6": "<p>{}</p>",
  "mn97:4.1": "<p id=\"p3\"><span class=\"parno\">{}</span>{}{}{}{}{}</p>",
  "mn97:4.2": "<p>{}</p>",
  "mn97:5.1": "<p><span class=\"parno\">{}</span>{}{}{}{}{}</p>",
  "mn97:6.1": "<p>{}</p>",
  "mn97:6.2": "<p id=\"p13\"><span class=\"parno\">{}</span>{}</p>",
  "mn97:6.3": "<p>{}</p>",
  "mn97:6.4": "<p>{}</p>",
  "mn97:7.1": "<p><span class=\"parno\">{}</span>{}</p>",
  "mn97:8.1": "<p>{}</p>",
  "mn97:8.2": "<p>{}</p>",
  "mn97:9.1": "<p id=\"p23\"><span class=\"parno\">{}</span>{}</p>",
  "mn97:9.2": "<p>{}</p>",
  "mn97:9.3": "<p>{}</p>",
  "mn97:10.1": "<p id=\"p24\"><span class=\"parno\">{}</span>{}</p>",
  "mn97:10.2": "<p>{}</p>",
  "mn97:10.3": "<p id=\"p25\"><span class=\"parno\">{}</span>{}</p>",
  "mn97:10.4": "<p>{}</p>",
  "mn97:11.1": "<p id=\"p26\"><span class=\"parno\">{}</span>{}{}</p>",
  "mn97:11.2": "<p>{}</p>",
  "mn97:11.3": "<p id=\"p27\"><span class=\"parno\">{}</span>{}</p>",
  "mn97:11.4": "<p>{}</p>",
  "mn97:11.5": "<p>{}{}</p>",
  "mn97:11.6": "<p id=\"p28\"><span class=\"parno\">{}</span>{}</p>",
  "mn97:11.7": "<p>{}</p>",
  "mn97:11.8": "<p>{}</p>",
  "mn97:11.9": "<p>{}</p>",
  "mn97:11.10": "<p>{}</p>"
}