{
  "sn12.44:1.0.1": "<p id=\"p1\">{}<span class=\"note\" id=\"n124\"><span class=\"details\"><span class=\"p\">{}<a href=\"sn0-abbr.html\" title=\"Abbreviations\">{}</a>{}<i>{}</i>{}<a href=\"sn2.26.html#n182\">{}</a>{}</span></span></span></p>",
  "sn12.44:1.0.2": "<p id=\"p2\">{}<span class=\"add\">{}</span>{}</p>",
  "sn12.44:1.0.3": "<p id=\"p3\">{}<span class=\"add\">{}</span>{}</p>",
  "sn12.44:1.0.4": "<p id=\"p4\">{}<span class=\"add\">{}</span>{}</p>",
  "sn12.44:1.0.5": "<p id=\"p5\">{}<a class=\"pts_pn\">{}</a>{}<span class=\"add\">{}</span>{}</p>"
}