{
  "sn6.14:1.0.1": "<p id=\"p1\">{}</p>",
  "sn6.14:1.0.2": "<p id=\"p2\">{}<span class=\"note\" id=\"n418\"><span class=\"details\"><span class=\"p\">{}<a href=\"../dn/dn14.html#p5\">{}</a>{}</span></span></span>{}</p>",
  "sn6.14:1.0.3": "<p id=\"p3\">{}<a class=\"pts_pn\">{}</a>{}</p>",
  "sn6.14:1.0.4": "<p id=\"p4\">{}<span class=\"note\" id=\"n419\"><span class=\"details\"><span class=\"p\">{}<i>{}</i>{}</span></span></span>{}</p>",
  "sn6.14:1.0.5": "<p id=\"p5\">{}<span class=\"note\" id=\"n420\"><span class=\"details\"><span class=\"p\">{}<a href=\"../an/an3.80.html\">{}</a>{}<br class=\"half\"/>{}<a href=\"../tha/tha3.html#p256\">{}</a>{}<i>{}</i>{}</span></span></span></p>",
  "sn6.14:1.0.6": "<p class=\"verse\" id=\"p6\"><span class=\"add\">{}</span>{}<br/>{}<br/>{}<br/>{}<a class=\"pts_pn\">{}</a></p>",
  "sn6.14:1.0.7": "<p class=\"verse\" id=\"p7\"><span class=\"add\">{}</span>{}<br/>{}<br/>{}<br/>{}</p>",
  "sn6.14:1.0.8": "<p id=\"p8\">{}</p>",
  "sn6.14:1.0.9": "<p class=\"verse\" id=\"p9\"><span class=\"add\">{}</span>{}<br/>{}<br/>{}<br/>{}<a class=\"pts_pn\">{}</a></p>",
  "sn6.14:1.0.10": "<p class=\"verse\" id=\"p10\"><span class=\"add\">{}</span>{}<br/>{}<br/>{}<br/>{}</p>",
  "sn6.14:1.0.11": "<p id=\"p11\">{}</p>",
  "sn6.14:1.0.12": "<p id=\"p12\">{}</p>"
}