{
  "an9.37:1.0.1": "<p id=\"p1\">{}</p>",
  "an9.37:1.0.2": "<p id=\"p2\">{}<span class=\"note\" id=\"n1922\"><span class=\"details\"><span class=\"p\">{}<i>{}</i>{}<a href=\"../an/an9.42.html\">{}</a>{}</span></span></span>{}<span class=\"note\" id=\"n1923\"><span class=\"details\"><span class=\"p\">{}<a href=\"../dn/dn22.html\">{}</a>{}<small>{}</small>{}<a href=\"../mn/mn10.html#p2\">{}</a>{}<small>{}</small>{}<small>{}</small>{}<a href=\"../an/an3.74.html\">{}</a>{}<a href=\"../an/an4.194.html\">{}</a>{}<a href=\"../an/an6.26.html\">{}</a>{}<a href=\"../an/an10.95.html\">{}</a>{}</span></span></span>{}<a class=\"pts_pn\" id=\"an.iv.427\"></a>{}<span class=\"note\" id=\"n1924\"><span class=\"details\"><span class=\"p\">{}<a href=\"an0-abbr.html\">{}</a>{}<i>{}</i>{}<i>{}</i> <i>{}</i>{}<i>{}</i> <i>{}</i>{}<i>{}</i> <i>{}</i>{}</span></span></span>{}</p>",
  "an9.37:1.0.3": "<p id=\"p3\">{}</p>",
  "an9.37:1.0.4": "<p id=\"p4\">{}</p>",
  "an9.37:1.0.5": "<p id=\"p5\">{}<span class=\"add\">{}</span>{}</p>",
  "an9.37:1.0.6": "<p id=\"p6\">{}<span class=\"add\">{}</span>{}<span class=\"note\" id=\"n1925\"><span class=\"details\"><span class=\"p\">{}<a href=\"an0-abbr.html\">{}</a>{}<i>{}</i>{}<i>{}</i>{}<i>{}</i>{}</span></span></span></p>",
  "an9.37:1.0.7": "<p id=\"p7\">{}<span class=\"note\" id=\"n1926\"><span class=\"details\"><span class=\"p\">{}<a href=\"an0-abbr.html\">{}</a>{}<a href=\"an0-abbr.html\">{}</a>{}<i>{}</i>{}<i>{}</i>{}</span></span></span> <a class=\"pts_pn\" id=\"an.iv.428\"></a>{}<span class=\"note\" id=\"n1927\"><span class=\"details\"><span class=\"p\">{}<a href=\"an0-abbr.html\">{}</a>{}<i>{}</i>{}<i>{}</i>{}<i>{}</i>{}</span></span></span>{}<span class=\"add\">{}</span><span class=\"note\" id=\"n1928\"><span class=\"details\"><span class=\"p\">{}<a href=\"../an/an5.27.html\">{}</a>{}<a href=\"an0-abbr.html\">{}</a>{}</span></span></span>{}<span class=\"note\" id=\"n1929\"><span class=\"details\"><span class=\"p\">{}<i>{}</i>{}<a href=\"../sn/sn22.45.html#n59 \">{}</a>{}<small>{}</small>{}<small>{}</small>{}<small>{}</small>{}<small>{}</small>{}<small>{}</small>{}<i>{}</i>{}<i>{}</i>{}<i>{}</i>{}<i>{}</i>{}<i>{}</i>{}<i>{}</i>{}<i>{}</i>{}</span></span></span>{}<span class=\"note\" id=\"n1930\"><span class=\"details\"><span class=\"p\">{}<i>{}</i>{}<a href=\"an0-abbr.html\">{}</a>{}</span></span></span></p>",
  "an9.37:1.0.8": "<p id=\"p8\">{}<span class=\"add\">{}</span>{}<span class=\"note\" id=\"n1931\"><span class=\"details\"><span class=\"p\">{}<i>{}</i>{}<i>{}</i>{}<i>{}</i>{}<i>{}</i>{}<i>{}</i>{}<a href=\"an0-abbr.html\">{}</a>{}<i>{}</i>{}<i>{}</i>{}<a href=\"an5.25.html\">{}</a>{}<i>{}</i>{}<a href=\"an3.101.html\">{}</a>{}<i>{}</i>{}<br class=\"half\"/>{}<a href=\"an0-abbr.html\">{}</a>{}<small>{}</small>{}<small>{}</small>{}<img alt=\"\" class=\"calibre122\" src=\"images/000096.jpg\"/>{}<i>{}</i>{}<img alt=\"\" class=\"calibre123\" src=\"images/000037.jpg\"/>{}</span></span></span>{}</p>"
}