{
  "sn35.29:0.1": "Linked Discourses 35.29 ",
  "sn35.29:0.2": "3. All ",
  "sn35.29:0.3": "Oppressed ",
  "sn35.29:1.1": "1\nThus have I heard. On one occasion the Blessed One was dwelling at Rājagaha in the Bamboo Grove, the Squirrel Sanctuary. There the Blessed One addressed the bhikkhus thus:",
  "sn35.29:2.1": "",
  "sn35.29:2.2": "\"Bhikkhus, all is weighed down.\nAnd what, bhikkhus, is the all that is weighed down? The eye is weighed down, forms are weighed down, eye-consciousness is weighed down, eye-contact is weighed down, and whatever feeling arises with eye-contact as condition—whether pleasant or painful or neither-painful-nor-pleasant—that too is weighed down. Weighed down by what? Weighed down by birth, aging, and death; by sorrow, lamentation, pain, displeasure, and despair, I say.",
  "sn35.29:3.1": "",
  "sn35.29:3.2": "\"The ear is weighed down … The mind is weighed down … Weighed down by what? Weighed down by birth … by despair, I say.",
  "sn35.29:4.1": "",
  "sn35.29:4.2": "\"Seeing thus … He understands: ‘ … there is no more for this state of being.’\""
}