{
  "sn17.8:0.1": "Saṁyutta Nikāya 17.8 ",
  "sn17.8:0.2": "1. Paṭhamavagga ",
  "sn17.8:0.3": "Siṅgālasutta ",
  "sn17.8:1.1": "Sāvatthiyaṁ vihārati. \"Dāruṇo, bhikkhave, lābhasakkārasiloko … pe … adhigamāya. Assuttha no tumhe, bhikkhave, rattiyā paccūsasamayaṁ jarasiṅgālassa vassamānassā\"ti?",
  "sn17.8:1.2": "\"Evaṁ, bhante\".",
  "sn17.8:2.1": "",
  "sn17.8:2.2": "\"Eso kho, bhikkhave, jarasiṅgālo ukkaṇḍakena nāma rogajātena phuṭṭho neva bilagato ramati, na rukkhamūlagato ramati, na ajjhokāsagato ramati; yena yena gacchati, yattha yattha tiṭṭhati, yattha yattha nisīdati, yattha yattha nipajjati; tattha tattha anayabyasanaṁ āpajjati. Evameva kho, bhikkhave, idhekacco bhikkhu lābhasakkārasilokena abhibhūto pariyādiṇṇacitto neva suññāgāragato ramati, na rukkhamūlagato ramati, na ajjhokāsagato ramati; yena yena gacchati, yattha yattha tiṭṭhati, yattha yattha nisīdati, yattha yattha nipajjati; tattha tattha anayabyasanaṁ āpajjati. Evaṁ dāruṇo kho, bhikkhave, lābhasakkārasiloko … pe … evañhi vo, bhikkhave, sikkhitabban\"ti.\nAṭṭhamaṁ."
}