{
  "an3.37:0.1": "<article id='an3.37'><header><ul><li class='division'>{}</li>",
  "an3.37:0.2": "<li>{}</li></ul>",
  "an3.37:0.3": "<h1 class='sutta-title'>{}</h1></header>",
  "an3.37:1.1": "<p id=\"p1\"><span class=\"parno\">{}</span>{} {}{}{}{}{}</p>",
  "an3.37:1.2": "<p id=\"p2\"><span class=\"parno\">{}</span>{}{}</p>",
  "an3.37:1.3": "<p id=\"p3\"><span class=\"parno\">{}</span>{}{}</p>",
  "an3.37:1.4": "<p id=\"p4\"><span class=\"parno\">{}</span>{} </p>",
  "an3.37:1.5": "<p id=\"p5\"><span class=\"parno\">{}</span>{}<br/>{}<br/>{}<br/>{}<br/>{}<br/>{}</p>",
  "an3.37:1.6": "<p id=\"p6\"><span class=\"parno\">{}</span>{}</p>",
  "an3.37:1.7": "<p id=\"p7\"><span class=\"parno\">{}</span>{}</p>",
  "an3.37:1.8": "<p class=\"verse\" id=\"p8\"><span class=\"parno\">{}</span>{}<br/>{}<br/>{}<br/>{}<br/>{}<br/>{}</p>",
  "an3.37:1.9": "<p id=\"p9\"><span class=\"parno\">{}</span>{}</p>"
}