{
  "an3.118:0.1": "<article id='an3.118'><header><ul><li class='division'>{}</li>",
  "an3.118:0.2": "<li>{}</li></ul>",
  "an3.118:0.3": "<h1 class='sutta-title'>{}</h1></header>",
  "an3.118:1.1": "<p><span class=\"parno\">{}</span>{}</p><p>{}</p>",
  "an3.118:1.2": "<p>{}</p>",
  "an3.118:2.1": "<hr/>",
  "an3.118:2.2": "<p id=\"note582\">{}</p>",
  "an3.118:2.3": "<p>{}</p>",
  "an3.118:3.1": "<hr/>",
  "an3.118:3.2": "<p id=\"p5\"><span class=\"parno\">{}</span>{}</p>",
  "an3.118:4.1": "<hr/>",
  "an3.118:4.2": "<p><span class=\"parno\">{}</span>{}</p>",
  "an3.118:4.3": "<p>{}</p>",
  "an3.118:5.1": "<hr/>",
  "an3.118:5.2": "<p>{}</p>",
  "an3.118:5.3": "<p>{}</p>"
}