{
  "an6.14:0.1": "<article id='an6.14'><header><ul><li class='division'>{}</li>",
  "an6.14:0.2": "<li>{}</li></ul>",
  "an6.14:0.3": "<h1 class='sutta-title'>{}</h1></header>",
  "an6.14:1.1": "<p id=\"p1\"><span class=\"parno\">{}</span>{}</p>",
  "an6.14:1.2": "<p>{}{}</p>",
  "an6.14:1.3": "<p id=\"p2\"><span class=\"parno\">{}</span>{}{}{}</p>",
  "an6.14:1.4": "<p id=\"p3\"><span class=\"parno\">{}</span>{}{}{}{}</p>",
  "an6.14:1.5": "<p id=\"p4\"><span class=\"parno\">{}</span>{}</p>",
  "an6.14:1.6": "<p id=\"p5\"><span class=\"parno\">{}</span>{}{}</p>",
  "an6.14:1.7": "<p class=\"verse\" id=\"p6\"><span class=\"parno\">{}</span>{}{}<br/>{}<br/>{}<br/>{}</p>",
  "an6.14:1.8": "<p class=\"verse\" id=\"p7\"><span class=\"parno\">{}</span>{}<br/>{}<br/>{}<br/>{}</p>"
}