{
  "sn45.18:0.1": "Saṁyutta Nikāya 45.18 ",
  "sn45.18:0.2": "2. Vihāravagga ",
  "sn45.18:0.3": "Paṭhamakukkuṭārāmasutta ",
  "sn45.18:1.1": "1\nEvaṁ me sutaṁ—​\nekaṁ samayaṁ āyasmā ca ānando āyasmā ca bhaddo pāṭaliputte vihāranti kukkuṭārāme. Atha kho āyasmā bhaddo sāyanhasamayaṁ paṭisallānā vuṭṭhito yenāyasmā ānando tenupasaṅkami; upasaṅkamitvā āyasmatā ānandena saddhiṁ sammodi. Sammodanīyaṁ kathaṁ sāraṇīyaṁ vītisāretvā ekamantaṁ nisīdi. Ekamantaṁ nisinno kho āyasmā bhaddo āyasmantaṁ Ānandaṁ etadavoca:",
  "sn45.18:1.2": "2\n\"‘Abrahmacariyaṁ, abrahmacariyan’ti, āvuso Ānanda, vuccati. Katamaṁ nu kho, āvuso, abrahmacariyan\"ti?",
  "sn45.18:1.3": "\"Sādhu sādhu, āvuso bhadda. Bhaddako kho te, āvuso bhadda, ummaṅgo, bhaddakaṁ paṭibhānaṁ, kalyāṇī paripucchā. Evañhi tvaṁ, āvuso bhadda, pucchasi: ‘abrahmacariyaṁ, abrahmacariyanti, āvuso Ānanda, vuccati. Katamaṁ nu kho, āvuso, abrahmacariyan’\"ti?",
  "sn45.18:2.1": "",
  "sn45.18:2.2": "\"Evamāvuso\"ti.",
  "sn45.18:2.3": "\"Ayameva kho, āvuso, aṭṭhaṅgiko micchāmaggo abrahmacariyaṁ, seyyathidaṁ – micchādiṭṭhi … pe … micchāsamādhī\"ti.\nAṭṭhamaṁ."
}