{
  "dhp116-128:1.0.116": "<p id=\"p116\">{}</p>",
  "dhp116-128:1.0.117": "<p id=\"p117\">{}</p>",
  "dhp116-128:1.0.118": "<p id=\"p118\">{}</p>",
  "dhp116-128:1.0.119": "<p id=\"p119\">{}</p>",
  "dhp116-128:1.0.120": "<p id=\"p120\">{}</p>",
  "dhp116-128:1.0.121": "<p id=\"p121\">{}</p>",
  "dhp116-128:1.0.122": "<p id=\"p122\">{}</p>",
  "dhp116-128:1.0.123": "<p id=\"p123\">{}</p>",
  "dhp116-128:1.0.124": "<p id=\"p124\">{}</p>",
  "dhp116-128:1.0.125": "<p id=\"125\">{}</p>",
  "dhp116-128:1.0.126": "<p id=\"p126\">{}</p>",
  "dhp116-128:1.0.127": "<p id=\"p127\">{}</p>",
  "dhp116-128:1.0.128": "<p id=\"p128\">{}</p>"
}