{
  "sn12.35:1.0.1": "Sāvatthiyaṁ vihārati. \"Avijjāpaccayā, bhikkhave, saṅkhārā; saṅkhārapaccayā viññāṇaṁ … pe … evametassa kevalassa dukkhakkhandhassa samudayo hotī\"ti.",
  "sn12.35:1.0.2": "\"Katamā nu kho, bhante, jāti, kassa ca panāyaṁ jātī\"ti?",
  "sn12.35:1.0.3": "\"Katamo nu kho, bhante, bhavo, kassa ca panāyaṁ bhavo\"ti?",
  "sn12.35:1.0.4": "\"Katame nu kho, bhante, saṅkhārā, kassa ca panime saṅkhārā\"ti?",
  "sn12.35:1.0.5": "\"Avijjāya tveva, bhikkhu, asesavirāganirodhā yānissa tāni visūkāyikāni visevitāni vipphanditāni kānici kānici. ‘Katamaṁ jarāmaraṇaṁ, kassa ca panidaṁ jarāmaraṇaṁ’ iti vā, ‘aññaṁ jarāmaraṇaṁ, aññassa ca panidaṁ jarāmaraṇaṁ’ iti vā, ‘taṁ jīvaṁ taṁ sarīraṁ’ iti vā, ‘aññaṁ jīvaṁ aññaṁ sarīraṁ’ iti vā. Sabbānissa tāni pahīnāni bhavanti ucchinnamūlāni tālāvatthukatāni anabhāvaṅkatāni āyatiṁ anup pāda dhammāni.",
  "sn12.35:1.0.6": ""
}