{
  "an5.117:0.1": "Numbered Discourses 5.117 ",
  "an5.117:0.2": "12. At Andhakavinda ",
  "an5.117:0.3": "Jealous ",
  "an5.117:1.1": "1\n\"Bhikkhus, possessing five qualities, a bhikkhunī is deposited in hell as if brought there. What five? (1) Without investigating and scrutinizing, she speaks praise of one who deserves dispraise. (2) Without investigating and scrutinizing, she speaks dispraise of one who deserves praise. (3) She is envious (4) and miserly. (5) She squanders gifts given out of faith. Possessing these five qualities, a bhikkhunī is deposited in hell as if brought there.",
  "an5.117:1.2": "2\n\"Bhikkhus, possessing five\nqualities, a bhikkhunī is deposited in heaven as if brought there. (1) Having investigated and scrutinized, she speaks dispraise of one who deserves dispraise. (2) Having investigated and scrutinized, she speaks praise of one who deserves praise. (3) She is free from envy (4) and from miserliness. (5) She does not squander gifts given out of faith. Possessing these five qualities, a bhikkhunī is deposited in heaven as if brought there.\""
}