{
  "an5.33:1.1": "<p id=\"p1\"><span class=\"parno\">{}</span>{}</p>",
  "an5.33:2.1": "<p id=\"p2\"><span class=\"parno\">{}</span>{}{}{}</p>",
  "an5.33:2.2": "<p>{}</p>",
  "an5.33:2.3": "<p id=\"p3\"><span class=\"parno\">{}</span>{}</p>",
  "an5.33:2.4": "<p>{}</p>",
  "an5.33:3.1": "<p id=\"p4\"><span class=\"parno\">{}</span>{}</p>",
  "an5.33:3.2": "<p>{}</p>",
  "an5.33:3.3": "<p id=\"p5\"><span class=\"parno\">{}</span>{}</p>",
  "an5.33:3.4": "<p id=\"p6\"><span class=\"parno\">{}</span>{}</p>",
  "an5.33:3.5": "<p id=\"p7\"><span class=\"parno\">{}</span>{}{}</p>",
  "an5.33:3.6": "<p id=\"p8\"><span class=\"parno\">{}</span>{}</p>",
  "an5.33:4.1": "<p>{}</p>",
  "an5.33:4.2": "<p class=\"verse\" id=\"p9\"><span class=\"parno\">{}</span>{}<br/>{}<br/>{}<br/>{}</p>",
  "an5.33:4.3": "<p class=\"verse\"><span class=\"parno\">{}</span>{}<br/>{}\n<br/>{}<br/>{}</p>",
  "an5.33:4.4": "<p class=\"verse\" id=\"p10\"><span class=\"parno\">{}</span>{}<br/>{}<br/>{}<br/>{}</p>",
  "an5.33:4.5": "<p class=\"verse\" id=\"p12\"><span class=\"parno\">{}</span>{}<br/>{}<br/>{}<br/>{}</p>"
}