{
  "an4.212:0.1": "Aṅguttara Nikāya 4.212 ",
  "an4.212:0.2": "22. Parisāvagga ",
  "an4.212:0.3": "Diṭṭhisutta ",
  "an4.212:1.1": "\"Catūhi, bhikkhave, dhammehi samannāgato yathābhataṁ nikkhitto evaṁ niraye. Katamehi catūhi? Kāyaduccaritena, vacīduccaritena, manoduccaritena, micchādiṭṭhiyā – imehi kho, bhikkhave, catūhi dhammehi samannāgato yathābhataṁ nikkhitto evaṁ niraye.",
  "an4.212:1.2": "Catūhi, bhikkhave, dhammehi samannāgato yathābhataṁ nikkhitto evaṁ sagge. Katamehi catūhi? Kāyasucaritena, vacīsucaritena, manosucaritena, sammādiṭṭhiyā – imehi kho, bhikkhave, catūhi dhammehi samannāgato yathābhataṁ nikkhitto evaṁ sagge\"ti.\nDutiyaṁ."
}