{
  "sn46.111-120:0.1": "Linked Discourses 46.111–120 ",
  "sn46.111-120:0.2": "12. Searches ",
  "sn46.111-120:0.3": "Searches, Etc. ",
  "sn46.111-120:1.1": "\"Bhikkhus, there are these three searches. What three? The search for sensual pleasures, the search for existence, the search for a holy life … .\"",
  "sn46.111-120:2.1": "",
  "sn46.111-120:3.1": "",
  "sn46.111-120:3.2": "Searches, discriminations, taints,\nKinds of existence, threefold suffering,\nBarrenness, stains, and troubles,\nFeelings, craving, and thirst."
}