{
  "sn14.39:0.1": "Saṁyutta Nikāya 14.39 ",
  "sn14.39:0.2": "4. Catutthavagga ",
  "sn14.39:0.3": "Tatiyasamaṇabrāhmaṇasutta ",
  "sn14.39:1.1": "1\nSāvatthiyaṁ vihārati. \"Ye hi keci, bhikkhave, samaṇā vā brāhmaṇā vā pathavīdhātuṁ nappajānanti, pathavīdhātusamudayaṁ nappajānanti, pathavīdhātunirodhaṁ nappajānanti, pathavīdhātunirodhagāminiṁ paṭipadāṁ nappajānanti … pe … āpodhātuṁ nappajānanti … tejodhātuṁ nappajānanti … vāyodhātuṁ nappajānanti, vāyodhātusamudayaṁ nappajānanti, vāyodhātunirodhaṁ nappajānanti, vāyodhātunirodhagāminiṁ paṭipadāṁ nappajānanti, na me te, bhikkhave, samaṇā vā brāhmaṇā vā samaṇesu vā samaṇasammatā brāhmaṇesu vā brāhmaṇasammatā; na ca pana te āyasmanto sāmaññatthaṁ vā brahmaññatthaṁ vā diṭṭheva dhamme sayaṁ abhiññā sacchikatvā upasampajja vihāranti.",
  "sn14.39:1.2": "2\nYe ca kho keci, bhikkhave, samaṇā vā brāhmaṇā vā pathavīdhātuṁ pajānanti, pathavīdhātusamudayaṁ pajānanti, pathavīdhātunirodhaṁ pajānanti, pathavīdhātunirodhagāminiṁ paṭipadāṁ pajānanti … ye ca kho keci, bhikkhave, samaṇā vā brāhmaṇā vā … pe … āpodhātuṁ pajānanti … tejodhātuṁ pajānanti … vāyodhātuṁ pajānanti, vāyodhātusamudayaṁ pajānanti, vāyodhātunirodhaṁ pajānanti, vāyodhātunirodhagāminiṁ paṭipadāṁ pajānanti, te ca kho me, bhikkhave, samaṇā vā brāhmaṇā vā samaṇesu ceva samaṇasammatā brāhmaṇesu ca brāhmaṇasammatā; te ca panāyasmanto sāmaññatthañca brahmaññatthañca diṭṭheva dhamme sayaṁ abhiññā sacchikatvā upasampajja vihārantī\"ti.\nDasamaṁ.\nCatuttho vaggo.\n3\nCatasso pubbe acariṁ,\nnocedañca dukkhena ca;\nAbhinandañca uppādo,\ntayo samaṇabrāhmaṇāti.",
  "sn14.39:1.3": "Dhātusaṁyuttaṁ samattaṁ."
}